{
  "for": "WebMapLayers",
  "layer_groups": [
    {
      "group_name": "Working TEST Layers",
      "layers": [
        {
          "layer_name": "Wards",
          "data_source_type": "geojson",
          "data_source": "https://opendata.arcgis.com/datasets/3b5d399346244c81b97c43514613566e_0.geojson",
          "id_property_field":"CLV_WARDSOBJECTID",
          "display_fields": [
              ["WARD_LUTWARD","Ward Number","text"],
              ["WARD_LUTNAME","Ward Councilperson","text"],
              ["WARD_LUTURL","Ward URL Link","link"],
              ["WARD_LUTURLPIC","Councilperson Image","image"]            
            ],
          "layer_style": {
              "layer_style_rules": {
                "function": "var ward = feature.getProperty('CLV_WARDSWARD');var color = 'black';if (ward == '1') {color = 'yellow';} else if (ward == '2') {color = 'orange';} else if (ward == '3') {color = 'blue';} else if (ward == '4') {color = 'green';} else if (ward == '5') {color = 'grey';} else if (ward == '6') {color = 'rgb(132, 77, 45)';}return {fillColor: color,fillOpacity: 0.5,strokeColor: color,strokeOpacity: 1.0,strokeWeight: 1,zIndex: 1};",
                "parameters": "feature"
              }             
          },
          "legend": [
              ["Ward 1",{"fillColor": "rgba(255, 250, 5, 0.5)", "borderColor": "rgba(255, 250, 5, 1)", "borderWidth": "1px"}],
              ["Ward 2",{"fillColor": "rgba(255, 159, 5, 0.5)", "borderColor": "rgba(255, 159, 5, 1)", "borderWidth": "1px"}],
              ["Ward 3",{"fillColor": "rgba(5, 38, 255, 0.5)", "borderColor": "rgba(5, 38, 255, 1)", "borderWidth": "1px"}],
              ["Ward 4",{"fillColor": "rgba(3, 178, 20, 0.5)", "borderColor": "rgba(3, 178, 20, 1)", "borderWidth": "1px"}],
              ["Ward 5",{"fillColor": "rgba(170, 170, 170, 0.5)", "borderColor": "rgba(170, 170, 170, 1)", "borderWidth": "1px"}],
              ["Ward 6",{"fillColor": "rgba(132, 77, 45, 0.5)", "borderColor": "rgba(132, 77, 45, 1)", "borderWidth": "1px"}]
            ],
          "toggled": true,
          "min_zoom": "10",
          "max_zoom": "17"
        },
        {
          "layer_name": "Sewer Mains",
          "data_source_type": "MapServer",
          "data_source": "https://mapdata.lasvegasnevada.gov/clvgis/rest/services/ExistingInfrastructure/CollectionSystems/MapServer",
          "id_property_field":"OBJECTID",
          "mapserver_layer_number": "6",          
          "legend": [
              ["Sewer Mains", {"lineColor": "black", "lineWidth": "4px"}]
            ],
          "toggled": false,
          "min_zoom": "17",
          "max_zoom": "20"
        },
        {
          "layer_name": "Medical Marijuana",
          "data_source": "https://opendata.arcgis.com/datasets/892309e55f234e92a329d03374608ae3_0.geojson",
          "id_property_field":"OBJECTID",
          "layer_style": {
            "icon": "https://www.emeraldcitypilates.com/favicon.ico"
          },
          "legend": [
              ["Medical Marijuana",{"icon": "https://www.emeraldcitypilates.com/favicon.ico"}]
            ],
          "toggled": false
        },
        {
          "layer_name": "Precincts",
          "data_source": "https://opendata.arcgis.com/datasets/3e738fdaca2b4aeba0c18a2478cae956_0.geojson",
          "id_property_field":"OBJECTID",
          "layer_style": {
            "zIndex": 5000,
            "fillColor":"black",
            "fillOpacity": 0,
            "strokeColor":"black",
            "strokeOpacity": 1.0,
            "strokeWeight": 2
          },
          "legend": [
              ["Precincts",{"fillColor": "rgba(0, 0, 0, 0)", "borderColor": "rgba(0, 0, 0, 1)", "borderWidth": "2px"}]
            ],
          "toggled": false
        },
        {
          "layer_name": "Planning Cases by Parcel",
          "data_source": "https://opendata.arcgis.com/datasets/f0b7d04f2e234404bf330ecac5685fc3_0.geojson",
          "id_property_field":"OBJECTID_1",
          "layer_style": {
            "zIndex": 5000,
            "fillColor":"black",
            "fillOpacity": 0,
            "strokeColor":"grey",
            "strokeOpacity": 1.0,
            "strokeWeight": 1
          },
          "toggled": false
        },
        {
          "layer_name": "Sewer Mains geojson",
          "data_source": "https://opendata.arcgis.com/datasets/f5ad99485507440aa0e43bee51ef7d5c_6.geojson",
          "id_property_field":"OBJECTID",
          "layer_style": {
            "zIndex": 5000,
            "lineColor":"#ffffff",
            "lineOpacity": 1.0,
            "lineWeight": 1
          },
          "toggled": false
        },
        {
          "layer_name": "Animal Control Beats",
          "data_source": "https://opendata.arcgis.com/datasets/7c2209fbbafd4fc6aaccbaf3213b5451_0.geojson",
          "id_property_field":"OBJECTID"
        },
        {
          "layer_name": "Phantoms VERY LARGE",
          "data_source": "",
          "id_property_field":"OBJECTID"
        },
        {
          "layer_name": "Park Hardscapes",
          "data_source": "https://opendata.arcgis.com/datasets/6e53b3f63e384269b9714d71870458e0_21.geojson",
          "id_property_field":"OBJECTID"
        },
        {
          "layer_name": "City Parks",
          "data_source": "https://opendata.arcgis.com/datasets/c258a90169ea490eb1abcb029ac4573b_0.geojson",
          "id_property_field":"OBJECTID"
        },
        {
          "layer_name": "Through Streets",
          "data_source": "https://opendata.arcgis.com/datasets/64a16dd208684f4d96bb8b77edcbe6f9_0.geojson",
          "id_property_field":"OBJECTID"
        },
        {
          "layer_name": "Environmental Compliance - Class II Permits",
          "data_source": "https://opendata.arcgis.com/datasets/3c03b34501364516977589543a1e47c2_0.geojson",
          "id_property_field":"OBJECTID"
        },
        {
          "layer_name": "Private Parks",
          "data_source": "https://opendata.arcgis.com/datasets/54366d0ab8f24786b5274498cf92680c_1.geojson",
          "id_property_field":"OBJECTID_12"
        },
        {
          "layer_name": "Park Structures",
          "data_source": "https://opendata.arcgis.com/datasets/d87f1a0957124d0888b65a0db9bbb006_18.geojson",
          "id_property_field":"OBJECTID"
        },
        {
          "layer_name": "Jurisdictions",
          "data_source": "https://opendata.arcgis.com/datasets/13f35f74589b4bb0b8d9a4de4c444158_0.geojson",
          "id_property_field":"OBJECTID"
        },
        {
          "layer_name": "City Limits",
          "data_source": "https://opendata.arcgis.com/datasets/edfc142e2eac413baee3ed19d73195b5_0.geojson",
          "id_property_field":"OBJECTID"
        },
        {
          "layer_name": "City Facilities",
          "data_source": "https://opendata.arcgis.com/datasets/53385f4e5f2d476ab238c1ec472e15f7_0.geojson",
          "id_property_field":"OBJECTID"
        },
        {
          "layer_name": "Parking Meter Zones",
          "data_source": "https://opendata.arcgis.com/datasets/0281be85aee14279ac9e8315ee5051f2_3.geojson",
          "id_property_field":"OBJECTID",
          "layer_style": {
              "layer_style_rules": {
                "function": "var time = feature.getProperty('TIME_LIMIT');var color = 'black';if (time == 'None') {color = 'green';} else if (time == '4HR') {color = 'orange';} else if (time == '2HR') {color = 'yellow';} else if (time == '10HR') {color = 'blue';} return {fillColor: color,fillOpacity: 0.5,strokeColor: color,strokeOpacity: 1.0,strokeWeight: 4,zIndex: 1};",
                "parameters": "feature"
              }             
          },
          "legend": [
            ["Parking Meter Zones - No Limit", {"lineColor": "green", "lineWidth": "4px"}],
            ["Parking Meter Zones - 4HR Limit", {"lineColor": "orange", "lineWidth": "4px"}],
            ["Parking Meter Zones - 2HR Limit", {"lineColor": "yellow", "lineWidth": "4px"}],
            ["Parking Meter Zones - 10HR Limit", {"lineColor": "blue", "lineWidth": "4px"}]
          ]
        }
      ]
    }
  ]
}
